somecomfort/__init__.py
somecomfort/__main__.py
somecomfort/client.py
somecomfort-0.8.0.dist-info/LICENSE
somecomfort-0.8.0.dist-info/METADATA
somecomfort-0.8.0.dist-info/WHEEL
somecomfort-0.8.0.dist-info/entry_points.txt
somecomfort-0.8.0.dist-info/top_level.txt
somecomfort-0.8.0.dist-info/RECORD
