Metadata-Version: 2.1
Name: somecomfort
Version: 0.8.0
Summary: A client for Honeywell's US-based cloud devices
Home-page: https://github.com/kk7ds/somecomfort
Author: Dan Smith
Author-email: dsmith+somecomfort@danplanet.com
License: UNKNOWN
Platform: UNKNOWN
License-File: LICENSE
Requires-Dist: requests (>=2.9.0)
Requires-Dist: prettytable
